flask_composed_views/__init__.py
flask_composed_views/components/__init__.py
flask_composed_views/components/base_component.py
flask_composed_views/components/base_tag.py
flask_composed_views/components/container.py
flask_composed_views/components/div.py
flask_composed_views/components/form.py
flask_composed_views/components/form_hidden_input.py
flask_composed_views/components/form_submit.py
flask_composed_views/components/form_text_input.py
flask_composed_views/components/header_1.py
flask_composed_views/components/link.py
flask_composed_views/components/paragraph.py
flask_composed_views/components/plain_text.py
flask_composed_views/components/span.py
flask_composed_views/components/tag_builder.py
flask_composed_views/core/__init__.py
flask_composed_views/core/plain_text_utils.py
flask_composed_views/utils/__init__.py
flask_composed_views/utils/base_page.py
flask_composed_views-0.0.3.dist-info/licenses/LICENSE.md
flask_composed_views-0.0.3.dist-info/METADATA
flask_composed_views-0.0.3.dist-info/WHEEL
flask_composed_views-0.0.3.dist-info/top_level.txt
flask_composed_views-0.0.3.dist-info/RECORD
