Metadata-Version: 2.4
Name: flask_composed_views
Version: 0.0.3
Summary: Class-based components for Flask
Author-email: Alexandre De Zotti <alexn11.gh@gmail.com>
License-Expression: MIT
Project-URL: Homepage, https://github.com/alexn11/flask-composed-views
Project-URL: Issues, https://github.com/alexn11/flask-composed-views/issues
Classifier: Programming Language :: Python :: 3
Classifier: Operating System :: OS Independent
Requires-Python: >=3.9
License-File: LICENSE.md
Dynamic: license-file
